brain_loop_search/__init__.py
brain_loop_search/brain_utils.py
brain_loop_search/packing.py
brain_loop_search/search.py
brain_loop_search/structures.csv
brain_loop_search-0.1.7.dist-info/LICENSE
brain_loop_search-0.1.7.dist-info/METADATA
brain_loop_search-0.1.7.dist-info/WHEEL
brain_loop_search-0.1.7.dist-info/top_level.txt
brain_loop_search-0.1.7.dist-info/RECORD
