Metadata-Version: 2.1
Name: brain-loop-search
Version: 0.1.7
Summary: Screen loops among brain structures(or any entities comprising a graph).
Author-email: Zuohan Zhao <zzhmark@126.com>
License: MIT License
Project-URL: GitHub Project, https://github.com/SEU-ALLEN-codebase/brain-loop-search
Project-URL: Documentation, https://SEU-ALLEN-codebase.github.io/brain-loop-search
Keywords: neuron-morphology
Classifier: Programming Language :: Python :: 3
Classifier: License :: OSI Approved :: MIT License
Classifier: Operating System :: OS Independent
Requires-Python: >=3.10
License-File: LICENSE
Requires-Dist: networkx
Requires-Dist: numpy
Requires-Dist: pandas
Requires-Dist: importlib-resources
Requires-Dist: brainrender
Provides-Extra: docs
Requires-Dist: pdoc ; extra == 'docs'
